dialogflowpy_webhook/__init__.py
dialogflowpy_webhook/request_handler.py
dialogflowpy_webhook/response_handler.py
dialogflowpy_webhook-1.0.0.dist-info/METADATA
dialogflowpy_webhook-1.0.0.dist-info/RECORD
dialogflowpy_webhook-1.0.0.dist-info/WHEEL
dialogflowpy_webhook-1.0.0.dist-info/top_level.txt
