Metadata-Version: 2.1
Name: dialogflowpy-webhook
Version: 1.0.0
Summary: A Python module for parsing and creating Dialogflow Requests and Responses
Home-page: https://github.com/vishalbala-nps/dialogflowpy-webhook
Author: Vishal Balasubramanian
Author-email: vishal.bala.nps@gmail.com
License: MIT
Keywords: dialogflow,flask,django,fulfillment,webhook,api,python3,api.ai,python,Dialogflow Fulfillment,Dialogflow Fulfillment V2,dialogflowpy-webhook,artificial intelligence
Platform: UNKNOWN
Classifier: Intended Audience :: Developers
Classifier: Topic :: Software Development :: Build Tools
Classifier: License :: OSI Approved :: MIT License
Classifier: Programming Language :: Python :: 3
Requires-Python: >=3
